[
  {
    "inputs": [
      {
        "components": [
          {"internalType": "address", "name": "tokenIn", "type": "address"},
          {"internalType": "address", "name": "tokenOut", "type": "address"},
          {"internalType": "uint24", "name": "fee", "type": "uint24"},
          {"internalType": "uint256", "name": "amountIn", "type": "uint256"},
          {"internalType": "uint160", "name": "sqrtPriceLimitX96", "type": "uint160"}
        ],
        "internalType": "struct IQuoterV2.QuoteExactInputSingleParams",
        "name": "params",
        "type": "tuple"
      }
    ],
    "name": "quoteExactInputSingle",
    "outputs": [
      {"internalType": "uint256", "name": "amountOut", "type": "uint256"}
    ],
    "stateMutability": "view",
    "type": "function"
  }
] 